<?xml version="1.0"?>
<!--<!DOCTYPE metadata SYSTEM "http://www.esri.com/metadata/esriprof80.dtd">-->
<metadata xml:lang="hr"><Esri><CreaDate>20061117</CreaDate><CreaTime>09373300</CreaTime><SyncOnce>TRUE</SyncOnce><DataProperties><lineage><Process Name="AddXY_1" ToolSource="C:\Program Files\ArcGIS\ArcToolbox\Toolboxes\Data Management Tools.tbx\AddXY" Date="20061117" Time="093511">AddXY D:\Institut\Arboretum_Opeke\Poztocke.shp D:\Institut\Arboretum_Opeke\Poztocke.shp</Process></lineage></DataProperties><MetaID>{C1AD941E-A647-449C-B96D-F4BA540F07EA}</MetaID></Esri><idinfo><citation><citeinfo><onlink Sync="TRUE"></onlink></citeinfo></citation></idinfo><distInfo><distributor><distorTran><onLineSrc><linkage Sync="TRUE">file://</linkage><protocol Sync="TRUE">Local Area Network</protocol></onLineSrc></distorTran></distributor></distInfo><dataqual><lineage><procstep><procdesc Sync="TRUE">Dataset copied.</procdesc><srcused Sync="TRUE"></srcused><date Sync="TRUE">20061117</date><time Sync="TRUE">09373300</time></procstep></lineage></dataqual></metadata>
